zyjj_open_sdk/__init__.py
zyjj_open_sdk/core/__init__.py
zyjj_open_sdk/core/client/__init__.py
zyjj_open_sdk/core/client/async_client.py
zyjj_open_sdk/core/client/async_mqtt.py
zyjj_open_sdk/core/client/base.py
zyjj_open_sdk/core/client/sync_client.py
zyjj_open_sdk/core/client/sync_mqtt.py
zyjj_open_sdk/core/entity/__init__.py
zyjj_open_sdk/core/entity/async_task.py
zyjj_open_sdk/core/entity/task.py
zyjj_open_sdk/core/entity/type.py
zyjj_open_sdk/core/exception/__init__.py
zyjj_open_sdk/core/lib/__init__.py
zyjj_open_sdk/core/lib/file.py
zyjj_open_sdk/core/lib/utils.py
zyjj_open_sdk/task/__init__.py
zyjj_open_sdk/task/audio/__init__.py
zyjj_open_sdk/task/audio/audio_async_test.py
zyjj_open_sdk/task/audio/audio_test.py
zyjj_open_sdk/task/audio/entity.py
zyjj_open_sdk/task/image/__init__.py
zyjj_open_sdk/task/image/entity.py
zyjj_open_sdk/task/image/image_async_test.py
zyjj_open_sdk/task/image/image_test.py
zyjj_open_sdk/task/subtitle/__init__.py
zyjj_open_sdk/task/subtitle/entity.py
zyjj_open_sdk/task/subtitle/subtitle_async_test.py
zyjj_open_sdk/task/subtitle/subtitle_test.py
zyjj_open_sdk/task/text/__init__.py
zyjj_open_sdk/task/text/entity.py
zyjj_open_sdk/task/text/text_async_test.py
zyjj_open_sdk/task/text/text_test.py
zyjj_open_sdk/task/tool/__init__.py
zyjj_open_sdk/task/tool/entity.py
zyjj_open_sdk/task/tool/tool_async_test.py
zyjj_open_sdk/task/tool/tool_test.py
zyjj_open_sdk/task/video/__init__.py
zyjj_open_sdk-0.1.5.dist-info/METADATA
zyjj_open_sdk-0.1.5.dist-info/WHEEL
zyjj_open_sdk-0.1.5.dist-info/RECORD
