Metadata-Version: 2.3
Name: zyjj-open-sdk
Version: 0.1.5
Summary: 智游剪辑开放平台python sdk
Author: zyjj
Author-email: zyjj.cc@foxmail.com
Requires-Python: >=3.10
Classifier: Programming Language :: Python :: 3
Classifier: Programming Language :: Python :: 3.10
Classifier: Programming Language :: Python :: 3.11
Classifier: Programming Language :: Python :: 3.12
Classifier: Programming Language :: Python :: 3.13
Requires-Dist: ffmpeg-python (>=0.2.0,<0.3.0)
Requires-Dist: httpx (>=0.28.1,<0.29.0)
Requires-Dist: paho-mqtt (>=2.1.0,<3.0.0)
